{
  "icon": true,
  "expandProps": false,
  "plugins": [
    {
      "name": "preset-default",
      "params": {
        "overrides": {
          "removeTitle": true,
          "cleanupListOfValues": true,
          "addAttributesToSVGElement": false,
          "addClassesToSVGElement": false,
          "cleanupAttrs": true,
          "cleanupEnableBackground": true,
          "cleanupIDs": true,
          "cleanupNumericValues": true,
          "collapseGroups": true,
          "convertColors": true,
          "convertPathData": true,
          "convertTransform": true,
          "mergePaths": true,
          "minifyStyles": true,
          "moveElemsAttrsToGroup": true,
          "moveGroupAttrsToElems": true,
          "removeComments": true,
          "removeDesc": true,
          "removeDoctype": true,
          "removeEditorsNSData": true,
          "removeElementsByAttr": false,
          "removeEmptyAttrs": true,
          "removeEmptyContainers": true,
          "removeMetadata": true,
          "removeNonInheritableGroupAttrs": true,
          "removeStyleElement": true,
          "removeUnknownsAndDefaults": true,
          "removeUnusedNS": true,
          "removeUselessDefs": true,
          "removeUselessStrokeAndFill": true,
          "removeViewBox": false,
          "removeXMLNS": false,
          "removeXMLProcInst": true,
          "sortAttrs": true,
          "inlineStyles": true,
          "removeRasterImages": false,
          "convertEllipseToCircle": true,
          "sortDefsChildren": true,
          "removeAttributesBySelector": false,
          "removeScriptElement": false,
          "removeOffCanvasPaths": false,
          "reusePaths": false
        }
      }
    }
  ]
}
